pystval-1.2.0.dist-info/METADATA
pystval-1.2.0.dist-info/WHEEL
pystval-1.2.0.dist-info/license_files/LICENSE
pystval/__init__.py
pystval/__init__.pyi
pystval/py.typed
pystval/pystval.abi3.so
pystval-1.2.0.dist-info/RECORD
