Metadata-Version: 2.1
Name: pystval
Version: 1.2.0
Classifier: Programming Language :: Rust
Classifier: Programming Language :: Python :: Implementation :: CPython
Classifier: Programming Language :: Python :: Implementation :: PyPy
License-File: LICENSE
Summary: Library for creating a custom validator
Keywords: validate,regex,rust
Author: Mansur Azatbek
Author-email: mansur62624@gmail.com
Requires-Python: >=3.7
